{
  "version": "roadgen3d_reference_annotation_v2",
  "plan_id": "scenario_07_asymmetric_shared_street_pocket_park",
  "image_path": "/api/graph-templates/hkust_gz_gate/image",
  "image_width_px": 1024,
  "image_height_px": 170,
  "pixels_per_meter": 1.5,
  "centerlines": [
    {
      "id": "centerline_04",
      "label": "centerline_04",
      "points": [
        {
          "x": 66.61957982729098,
          "y": 97.51053682342501
        },
        {
          "x": 291.7560039751718,
          "y": 99.22703610030007
        }
      ],
      "road_width_m": 25.500000000000004,
      "reference_width_px": null,
      "forward_drive_lane_count": 2,
      "reverse_drive_lane_count": 2,
      "bike_lane_count": 0,
      "bus_lane_count": 0,
      "parking_lane_count": 0,
      "highway_type": "annotated_centerline",
      "cross_section_mode": "detailed",
      "cross_section_strips": [
        {
          "strip_id": "left_01",
          "zone": "left",
          "kind": "nearroad_furnishing",
          "width_m": 1.5,
          "direction": "none",
          "order_index": 0
        },
        {
          "strip_id": "left_02",
          "zone": "left",
          "kind": "clear_sidewalk",
          "width_m": 2.5,
          "direction": "none",
          "order_index": 1
        },
        {
          "strip_id": "left_03",
          "zone": "left",
          "kind": "frontage_reserve",
          "width_m": 2,
          "direction": "none",
          "order_index": 2
        },
        {
          "strip_id": "center_01",
          "zone": "center",
          "kind": "drive_lane",
          "width_m": 3.3,
          "direction": "reverse",
          "order_index": 0
        },
        {
          "strip_id": "center_02",
          "zone": "center",
          "kind": "drive_lane",
          "width_m": 3.3,
          "direction": "reverse",
          "order_index": 1
        },
        {
          "strip_id": "center_03",
          "zone": "center",
          "kind": "median",
          "width_m": 0.3,
          "direction": "none",
          "order_index": 2
        },
        {
          "strip_id": "center_04",
          "zone": "center",
          "kind": "drive_lane",
          "width_m": 3.3,
          "direction": "forward",
          "order_index": 3
        },
        {
          "strip_id": "center_05",
          "zone": "center",
          "kind": "drive_lane",
          "width_m": 3.3,
          "direction": "forward",
          "order_index": 4
        },
        {
          "strip_id": "right_01",
          "zone": "right",
          "kind": "nearroad_furnishing",
          "width_m": 1.5,
          "direction": "none",
          "order_index": 0
        },
        {
          "strip_id": "right_02",
          "zone": "right",
          "kind": "clear_sidewalk",
          "width_m": 2.5,
          "direction": "none",
          "order_index": 1
        },
        {
          "strip_id": "right_03",
          "zone": "right",
          "kind": "frontage_reserve",
          "width_m": 2,
          "direction": "none",
          "order_index": 2
        }
      ],
      "street_furniture_instances": [
        {
          "instance_id": "centerline_04_furniture_01",
          "centerline_id": "centerline_04",
          "strip_id": "left_03",
          "kind": "tree",
          "station_m": 9.915619249945026,
          "lateral_offset_m": -1,
          "yaw_deg": null
        },
        {
          "instance_id": "centerline_04_furniture_02",
          "centerline_id": "centerline_04",
          "strip_id": "left_03",
          "kind": "tree",
          "station_m": 22.850848913681446,
          "lateral_offset_m": -1,
          "yaw_deg": null
        },
        {
          "instance_id": "centerline_04_furniture_03",
          "centerline_id": "centerline_04",
          "strip_id": "left_03",
          "kind": "tree",
          "station_m": 33.431605052250696,
          "lateral_offset_m": -1,
          "yaw_deg": null
        },
        {
          "instance_id": "centerline_04_furniture_04",
          "centerline_id": "centerline_04",
          "strip_id": "left_03",
          "kind": "tree",
          "station_m": 42.39552933929538,
          "lateral_offset_m": -1,
          "yaw_deg": null
        },
        {
          "instance_id": "centerline_04_furniture_05",
          "centerline_id": "centerline_04",
          "strip_id": "left_03",
          "kind": "tree",
          "station_m": 63.06309897815006,
          "lateral_offset_m": -0.364942412851633,
          "yaw_deg": null
        },
        {
          "instance_id": "centerline_04_furniture_06",
          "centerline_id": "centerline_04",
          "strip_id": "left_03",
          "kind": "tree",
          "station_m": 71.01496254519813,
          "lateral_offset_m": -0.5447282470061925,
          "yaw_deg": null
        },
        {
          "instance_id": "centerline_04_furniture_07",
          "centerline_id": "centerline_04",
          "strip_id": "left_03",
          "kind": "tree",
          "station_m": 81.65530634988095,
          "lateral_offset_m": 0.5011909126208494,
          "yaw_deg": null
        },
        {
          "instance_id": "centerline_04_furniture_08",
          "centerline_id": "centerline_04",
          "strip_id": "left_03",
          "kind": "tree",
          "station_m": 89.78916187266691,
          "lateral_offset_m": 0.5632055651850099,
          "yaw_deg": null
        },
        {
          "instance_id": "centerline_04_furniture_09",
          "centerline_id": "centerline_04",
          "strip_id": "left_03",
          "kind": "tree",
          "station_m": 115.44498533024223,
          "lateral_offset_m": 0.490115500506235,
          "yaw_deg": null
        },
        {
          "instance_id": "centerline_04_furniture_10",
          "centerline_id": "centerline_04",
          "strip_id": "left_03",
          "kind": "tree",
          "station_m": 125.12485472871323,
          "lateral_offset_m": 0.5639173692425263,
          "yaw_deg": null
        },
        {
          "instance_id": "centerline_04_furniture_11",
          "centerline_id": "centerline_04",
          "strip_id": "right_03",
          "kind": "tree",
          "station_m": 4.450251094409281,
          "lateral_offset_m": 1,
          "yaw_deg": null
        },
        {
          "instance_id": "centerline_04_furniture_12",
          "centerline_id": "centerline_04",
          "strip_id": "right_03",
          "kind": "tree",
          "station_m": 16.355570652476448,
          "lateral_offset_m": 1,
          "yaw_deg": null
        },
        {
          "instance_id": "centerline_04_furniture_13",
          "centerline_id": "centerline_04",
          "strip_id": "right_03",
          "kind": "tree",
          "station_m": 23.301635026870258,
          "lateral_offset_m": 1,
          "yaw_deg": null
        },
        {
          "instance_id": "centerline_04_furniture_14",
          "centerline_id": "centerline_04",
          "strip_id": "right_03",
          "kind": "tree",
          "station_m": 32.46533804401258,
          "lateral_offset_m": 1,
          "yaw_deg": null
        },
        {
          "instance_id": "centerline_04_furniture_15",
          "centerline_id": "centerline_04",
          "strip_id": "right_03",
          "kind": "tree",
          "station_m": 56.07067691848372,
          "lateral_offset_m": 1,
          "yaw_deg": null
        },
        {
          "instance_id": "centerline_04_furniture_16",
          "centerline_id": "centerline_04",
          "strip_id": "right_03",
          "kind": "tree",
          "station_m": 64.61303204256858,
          "lateral_offset_m": 1,
          "yaw_deg": null
        },
        {
          "instance_id": "centerline_04_furniture_17",
          "centerline_id": "centerline_04",
          "strip_id": "right_03",
          "kind": "tree",
          "station_m": 74.70215758805267,
          "lateral_offset_m": 1,
          "yaw_deg": null
        },
        {
          "instance_id": "centerline_04_furniture_18",
          "centerline_id": "centerline_04",
          "strip_id": "right_03",
          "kind": "tree",
          "station_m": 89.03494804061921,
          "lateral_offset_m": 1,
          "yaw_deg": null
        },
        {
          "instance_id": "centerline_04_furniture_19",
          "centerline_id": "centerline_04",
          "strip_id": "right_03",
          "kind": "tree",
          "station_m": 114.65325918815027,
          "lateral_offset_m": 1,
          "yaw_deg": null
        },
        {
          "instance_id": "centerline_04_furniture_20",
          "centerline_id": "centerline_04",
          "strip_id": "right_03",
          "kind": "tree",
          "station_m": 125.31087928118433,
          "lateral_offset_m": 1,
          "yaw_deg": null
        },
        {
          "instance_id": "centerline_04_furniture_21",
          "centerline_id": "centerline_04",
          "strip_id": "left_03",
          "kind": "trash",
          "station_m": 52.5354874490603,
          "lateral_offset_m": -1,
          "yaw_deg": null
        }
      ],
      "start_junction_id": "",
      "end_junction_id": "junction_01"
    },
    {
      "id": "centerline_05",
      "label": "centerline_05",
      "points": [
        {
          "x": 291.7560039751718,
          "y": 99.22703610030007
        },
        {
          "x": 516.1008267201856,
          "y": 100.9375
        }
      ],
      "road_width_m": 25.500000000000004,
      "reference_width_px": null,
      "forward_drive_lane_count": 2,
      "reverse_drive_lane_count": 2,
      "bike_lane_count": 0,
      "bus_lane_count": 0,
      "parking_lane_count": 0,
      "highway_type": "annotated_centerline",
      "cross_section_mode": "detailed",
      "cross_section_strips": [
        {
          "strip_id": "left_01",
          "zone": "left",
          "kind": "nearroad_furnishing",
          "width_m": 1.5,
          "direction": "none",
          "order_index": 0
        },
        {
          "strip_id": "left_02",
          "zone": "left",
          "kind": "clear_sidewalk",
          "width_m": 2.5,
          "direction": "none",
          "order_index": 1
        },
        {
          "strip_id": "left_03",
          "zone": "left",
          "kind": "frontage_reserve",
          "width_m": 2,
          "direction": "none",
          "order_index": 2
        },
        {
          "strip_id": "center_01",
          "zone": "center",
          "kind": "drive_lane",
          "width_m": 3.3,
          "direction": "reverse",
          "order_index": 0
        },
        {
          "strip_id": "center_02",
          "zone": "center",
          "kind": "drive_lane",
          "width_m": 3.3,
          "direction": "reverse",
          "order_index": 1
        },
        {
          "strip_id": "center_03",
          "zone": "center",
          "kind": "median",
          "width_m": 0.3,
          "direction": "none",
          "order_index": 2
        },
        {
          "strip_id": "center_04",
          "zone": "center",
          "kind": "drive_lane",
          "width_m": 3.3,
          "direction": "forward",
          "order_index": 3
        },
        {
          "strip_id": "center_05",
          "zone": "center",
          "kind": "drive_lane",
          "width_m": 3.3,
          "direction": "forward",
          "order_index": 4
        },
        {
          "strip_id": "right_01",
          "zone": "right",
          "kind": "nearroad_furnishing",
          "width_m": 1.5,
          "direction": "none",
          "order_index": 0
        },
        {
          "strip_id": "right_02",
          "zone": "right",
          "kind": "clear_sidewalk",
          "width_m": 2.5,
          "direction": "none",
          "order_index": 1
        },
        {
          "strip_id": "right_03",
          "zone": "right",
          "kind": "frontage_reserve",
          "width_m": 2,
          "direction": "none",
          "order_index": 2
        }
      ],
      "street_furniture_instances": [
        {
          "instance_id": "centerline_05_furniture_01",
          "centerline_id": "centerline_05",
          "strip_id": "right_03",
          "kind": "tree",
          "station_m": 13.98871135720055,
          "lateral_offset_m": 1,
          "yaw_deg": null
        },
        {
          "instance_id": "centerline_05_furniture_02",
          "centerline_id": "centerline_05",
          "strip_id": "right_03",
          "kind": "tree",
          "station_m": 32.13013993263586,
          "lateral_offset_m": 1,
          "yaw_deg": null
        },
        {
          "instance_id": "centerline_05_furniture_03",
          "centerline_id": "centerline_05",
          "strip_id": "right_03",
          "kind": "tree",
          "station_m": 48.62538518820628,
          "lateral_offset_m": 1,
          "yaw_deg": null
        },
        {
          "instance_id": "centerline_05_furniture_04",
          "centerline_id": "centerline_05",
          "strip_id": "right_03",
          "kind": "tree",
          "station_m": 70.94868861165077,
          "lateral_offset_m": 1,
          "yaw_deg": null
        },
        {
          "instance_id": "centerline_05_furniture_05",
          "centerline_id": "centerline_05",
          "strip_id": "right_03",
          "kind": "tree",
          "station_m": 103.55979052254781,
          "lateral_offset_m": 0.6395387366320495,
          "yaw_deg": null
        },
        {
          "instance_id": "centerline_05_furniture_06",
          "centerline_id": "centerline_05",
          "strip_id": "right_03",
          "kind": "tree",
          "station_m": 119.33335711484607,
          "lateral_offset_m": 0.8650794202972047,
          "yaw_deg": null
        },
        {
          "instance_id": "centerline_05_furniture_07",
          "centerline_id": "centerline_05",
          "strip_id": "left_03",
          "kind": "tree",
          "station_m": 28.11696436576929,
          "lateral_offset_m": -0.8540687468518566,
          "yaw_deg": null
        },
        {
          "instance_id": "centerline_05_furniture_08",
          "centerline_id": "centerline_05",
          "strip_id": "left_03",
          "kind": "tree",
          "station_m": 45.22267548753563,
          "lateral_offset_m": 0.6434036193858308,
          "yaw_deg": null
        },
        {
          "instance_id": "centerline_05_furniture_09",
          "centerline_id": "centerline_05",
          "strip_id": "left_03",
          "kind": "tree",
          "station_m": 69.20645745816442,
          "lateral_offset_m": 0.6015626088199326,
          "yaw_deg": null
        },
        {
          "instance_id": "centerline_05_furniture_10",
          "centerline_id": "centerline_05",
          "strip_id": "left_03",
          "kind": "tree",
          "station_m": 93.10505810434222,
          "lateral_offset_m": 0.19138178653644644,
          "yaw_deg": null
        },
        {
          "instance_id": "centerline_05_furniture_11",
          "centerline_id": "centerline_05",
          "strip_id": "left_03",
          "kind": "tree",
          "station_m": 112.37044661973022,
          "lateral_offset_m": 1,
          "yaw_deg": null
        }
      ],
      "start_junction_id": "junction_01",
      "end_junction_id": "junction_02"
    },
    {
      "id": "centerline_02",
      "label": "centerline_02",
      "points": [
        {
          "x": 291.7560039751718,
          "y": 99.22703610030007
        },
        {
          "x": 291.2388058229477,
          "y": 167.06285994032265
        }
      ],
      "road_width_m": 25.500000000000004,
      "reference_width_px": null,
      "forward_drive_lane_count": 2,
      "reverse_drive_lane_count": 2,
      "bike_lane_count": 0,
      "bus_lane_count": 0,
      "parking_lane_count": 0,
      "highway_type": "annotated_centerline",
      "cross_section_mode": "detailed",
      "cross_section_strips": [
        {
          "strip_id": "left_01",
          "zone": "left",
          "kind": "nearroad_furnishing",
          "width_m": 1.5,
          "direction": "none",
          "order_index": 0
        },
        {
          "strip_id": "left_02",
          "zone": "left",
          "kind": "clear_sidewalk",
          "width_m": 2.5,
          "direction": "none",
          "order_index": 1
        },
        {
          "strip_id": "left_03",
          "zone": "left",
          "kind": "frontage_reserve",
          "width_m": 2,
          "direction": "none",
          "order_index": 2
        },
        {
          "strip_id": "center_01",
          "zone": "center",
          "kind": "drive_lane",
          "width_m": 3.3,
          "direction": "reverse",
          "order_index": 0
        },
        {
          "strip_id": "center_02",
          "zone": "center",
          "kind": "drive_lane",
          "width_m": 3.3,
          "direction": "reverse",
          "order_index": 1
        },
        {
          "strip_id": "center_03",
          "zone": "center",
          "kind": "median",
          "width_m": 0.3,
          "direction": "none",
          "order_index": 2
        },
        {
          "strip_id": "center_04",
          "zone": "center",
          "kind": "drive_lane",
          "width_m": 3.3,
          "direction": "forward",
          "order_index": 3
        },
        {
          "strip_id": "center_05",
          "zone": "center",
          "kind": "drive_lane",
          "width_m": 3.3,
          "direction": "forward",
          "order_index": 4
        },
        {
          "strip_id": "right_01",
          "zone": "right",
          "kind": "nearroad_furnishing",
          "width_m": 1.5,
          "direction": "none",
          "order_index": 0
        },
        {
          "strip_id": "right_02",
          "zone": "right",
          "kind": "clear_sidewalk",
          "width_m": 2.5,
          "direction": "none",
          "order_index": 1
        },
        {
          "strip_id": "right_03",
          "zone": "right",
          "kind": "frontage_reserve",
          "width_m": 2,
          "direction": "none",
          "order_index": 2
        }
      ],
      "street_furniture_instances": [
        {
          "instance_id": "centerline_02_furniture_01",
          "centerline_id": "centerline_02",
          "strip_id": "left_03",
          "kind": "tree",
          "station_m": 22.301987629572462,
          "lateral_offset_m": -1,
          "yaw_deg": null
        },
        {
          "instance_id": "centerline_02_furniture_02",
          "centerline_id": "centerline_02",
          "strip_id": "left_03",
          "kind": "tree",
          "station_m": 28.82104172501803,
          "lateral_offset_m": -1,
          "yaw_deg": null
        },
        {
          "instance_id": "centerline_02_furniture_03",
          "centerline_id": "centerline_02",
          "strip_id": "left_03",
          "kind": "tree",
          "station_m": 37.168797796178794,
          "lateral_offset_m": -1,
          "yaw_deg": null
        },
        {
          "instance_id": "centerline_02_furniture_04",
          "centerline_id": "centerline_02",
          "strip_id": "right_03",
          "kind": "tree",
          "station_m": 21.720539603265163,
          "lateral_offset_m": 0.13324669818831403,
          "yaw_deg": null
        },
        {
          "instance_id": "centerline_02_furniture_05",
          "centerline_id": "centerline_02",
          "strip_id": "right_03",
          "kind": "tree",
          "station_m": 30.79257108707476,
          "lateral_offset_m": -0.1731129797427755,
          "yaw_deg": null
        },
        {
          "instance_id": "centerline_02_furniture_06",
          "centerline_id": "centerline_02",
          "strip_id": "right_03",
          "kind": "tree",
          "station_m": 40.18311208639201,
          "lateral_offset_m": -0.005671164563208819,
          "yaw_deg": null
        }
      ],
      "start_junction_id": "junction_01",
      "end_junction_id": ""
    },
    {
      "id": "centerline_03",
      "label": "centerline_03",
      "points": [
        {
          "x": 291.7560039751718,
          "y": 99.22703610030007
        },
        {
          "x": 292.27320212739585,
          "y": 31.3912122602775
        }
      ],
      "road_width_m": 25.500000000000004,
      "reference_width_px": null,
      "forward_drive_lane_count": 2,
      "reverse_drive_lane_count": 2,
      "bike_lane_count": 0,
      "bus_lane_count": 0,
      "parking_lane_count": 0,
      "highway_type": "annotated_centerline",
      "cross_section_mode": "detailed",
      "cross_section_strips": [
        {
          "strip_id": "left_01",
          "zone": "left",
          "kind": "nearroad_furnishing",
          "width_m": 1.5,
          "direction": "none",
          "order_index": 0
        },
        {
          "strip_id": "left_02",
          "zone": "left",
          "kind": "clear_sidewalk",
          "width_m": 2.5,
          "direction": "none",
          "order_index": 1
        },
        {
          "strip_id": "left_03",
          "zone": "left",
          "kind": "frontage_reserve",
          "width_m": 2,
          "direction": "none",
          "order_index": 2
        },
        {
          "strip_id": "center_01",
          "zone": "center",
          "kind": "drive_lane",
          "width_m": 3.3,
          "direction": "reverse",
          "order_index": 0
        },
        {
          "strip_id": "center_02",
          "zone": "center",
          "kind": "drive_lane",
          "width_m": 3.3,
          "direction": "reverse",
          "order_index": 1
        },
        {
          "strip_id": "center_03",
          "zone": "center",
          "kind": "median",
          "width_m": 0.3,
          "direction": "none",
          "order_index": 2
        },
        {
          "strip_id": "center_04",
          "zone": "center",
          "kind": "drive_lane",
          "width_m": 3.3,
          "direction": "forward",
          "order_index": 3
        },
        {
          "strip_id": "center_05",
          "zone": "center",
          "kind": "drive_lane",
          "width_m": 3.3,
          "direction": "forward",
          "order_index": 4
        },
        {
          "strip_id": "right_01",
          "zone": "right",
          "kind": "nearroad_furnishing",
          "width_m": 1.5,
          "direction": "none",
          "order_index": 0
        },
        {
          "strip_id": "right_02",
          "zone": "right",
          "kind": "clear_sidewalk",
          "width_m": 2.5,
          "direction": "none",
          "order_index": 1
        },
        {
          "strip_id": "right_03",
          "zone": "right",
          "kind": "frontage_reserve",
          "width_m": 2,
          "direction": "none",
          "order_index": 2
        }
      ],
      "street_furniture_instances": [
        {
          "instance_id": "centerline_03_furniture_01",
          "centerline_id": "centerline_03",
          "strip_id": "right_03",
          "kind": "tree",
          "station_m": 26.452480715758863,
          "lateral_offset_m": 1,
          "yaw_deg": null
        },
        {
          "instance_id": "centerline_03_furniture_02",
          "centerline_id": "centerline_03",
          "strip_id": "right_03",
          "kind": "tree",
          "station_m": 36.81126185336654,
          "lateral_offset_m": 1,
          "yaw_deg": null
        },
        {
          "instance_id": "centerline_03_furniture_03",
          "centerline_id": "centerline_03",
          "strip_id": "right_03",
          "kind": "tree",
          "station_m": 45.22519695913496,
          "lateral_offset_m": 1,
          "yaw_deg": null
        },
        {
          "instance_id": "centerline_03_furniture_04",
          "centerline_id": "centerline_03",
          "strip_id": "left_03",
          "kind": "tree",
          "station_m": 45.22519695913496,
          "lateral_offset_m": 0.5863883263227105,
          "yaw_deg": null
        },
        {
          "instance_id": "centerline_03_furniture_05",
          "centerline_id": "centerline_03",
          "strip_id": "left_03",
          "kind": "tree",
          "station_m": 35.58876036917583,
          "lateral_offset_m": 0.5000999244266584,
          "yaw_deg": null
        },
        {
          "instance_id": "centerline_03_furniture_06",
          "centerline_id": "centerline_03",
          "strip_id": "left_03",
          "kind": "tree",
          "station_m": 27.35480807349006,
          "lateral_offset_m": 0.732715912601746,
          "yaw_deg": null
        }
      ],
      "start_junction_id": "junction_01",
      "end_junction_id": ""
    },
    {
      "id": "centerline_01",
      "label": "centerline_01",
      "points": [
        {
          "x": 516.1008267201856,
          "y": 100.9375
        },
        {
          "x": 515.5779706392207,
          "y": 166.7025443883446
        }
      ],
      "road_width_m": 25.500000000000004,
      "reference_width_px": null,
      "forward_drive_lane_count": 2,
      "reverse_drive_lane_count": 2,
      "bike_lane_count": 0,
      "bus_lane_count": 0,
      "parking_lane_count": 0,
      "highway_type": "annotated_centerline",
      "cross_section_mode": "detailed",
      "cross_section_strips": [
        {
          "strip_id": "left_01",
          "zone": "left",
          "kind": "nearroad_furnishing",
          "width_m": 1.5,
          "direction": "none",
          "order_index": 0
        },
        {
          "strip_id": "left_02",
          "zone": "left",
          "kind": "clear_sidewalk",
          "width_m": 2.5,
          "direction": "none",
          "order_index": 1
        },
        {
          "strip_id": "left_03",
          "zone": "left",
          "kind": "frontage_reserve",
          "width_m": 2,
          "direction": "none",
          "order_index": 2
        },
        {
          "strip_id": "center_01",
          "zone": "center",
          "kind": "drive_lane",
          "width_m": 3.3,
          "direction": "reverse",
          "order_index": 0
        },
        {
          "strip_id": "center_02",
          "zone": "center",
          "kind": "drive_lane",
          "width_m": 3.3,
          "direction": "reverse",
          "order_index": 1
        },
        {
          "strip_id": "center_03",
          "zone": "center",
          "kind": "median",
          "width_m": 0.3,
          "direction": "none",
          "order_index": 2
        },
        {
          "strip_id": "center_04",
          "zone": "center",
          "kind": "drive_lane",
          "width_m": 3.3,
          "direction": "forward",
          "order_index": 3
        },
        {
          "strip_id": "center_05",
          "zone": "center",
          "kind": "drive_lane",
          "width_m": 3.3,
          "direction": "forward",
          "order_index": 4
        },
        {
          "strip_id": "right_01",
          "zone": "right",
          "kind": "nearroad_furnishing",
          "width_m": 1.5,
          "direction": "none",
          "order_index": 0
        },
        {
          "strip_id": "right_02",
          "zone": "right",
          "kind": "clear_sidewalk",
          "width_m": 2.5,
          "direction": "none",
          "order_index": 1
        },
        {
          "strip_id": "right_03",
          "zone": "right",
          "kind": "frontage_reserve",
          "width_m": 2,
          "direction": "none",
          "order_index": 2
        }
      ],
      "street_furniture_instances": [
        {
          "instance_id": "centerline_01_furniture_01",
          "centerline_id": "centerline_01",
          "strip_id": "right_03",
          "kind": "tree",
          "station_m": 18.733521650869502,
          "lateral_offset_m": -1,
          "yaw_deg": null
        },
        {
          "instance_id": "centerline_01_furniture_02",
          "centerline_id": "centerline_01",
          "strip_id": "right_03",
          "kind": "tree",
          "station_m": 32.82117906184311,
          "lateral_offset_m": -0.9805554924724973,
          "yaw_deg": null
        },
        {
          "instance_id": "centerline_01_furniture_03",
          "centerline_id": "centerline_01",
          "strip_id": "left_03",
          "kind": "tree",
          "station_m": 20.396434304420534,
          "lateral_offset_m": -1,
          "yaw_deg": null
        },
        {
          "instance_id": "centerline_01_furniture_04",
          "centerline_id": "centerline_01",
          "strip_id": "left_03",
          "kind": "tree",
          "station_m": 33.61831577528232,
          "lateral_offset_m": -1,
          "yaw_deg": null
        }
      ],
      "start_junction_id": "junction_02",
      "end_junction_id": ""
    },
    {
      "id": "centerline_08",
      "label": "centerline_08",
      "points": [
        {
          "x": 516.1008267201856,
          "y": 100.9375
        },
        {
          "x": 516.3304427869864,
          "y": 69.47532588086321
        }
      ],
      "road_width_m": 25.500000000000004,
      "reference_width_px": null,
      "forward_drive_lane_count": 2,
      "reverse_drive_lane_count": 2,
      "bike_lane_count": 0,
      "bus_lane_count": 0,
      "parking_lane_count": 0,
      "highway_type": "annotated_centerline",
      "cross_section_mode": "detailed",
      "cross_section_strips": [
        {
          "strip_id": "left_01",
          "zone": "left",
          "kind": "nearroad_furnishing",
          "width_m": 1.5,
          "direction": "none",
          "order_index": 0
        },
        {
          "strip_id": "left_02",
          "zone": "left",
          "kind": "clear_sidewalk",
          "width_m": 2.5,
          "direction": "none",
          "order_index": 1
        },
        {
          "strip_id": "left_03",
          "zone": "left",
          "kind": "frontage_reserve",
          "width_m": 2,
          "direction": "none",
          "order_index": 2
        },
        {
          "strip_id": "center_01",
          "zone": "center",
          "kind": "drive_lane",
          "width_m": 3.3,
          "direction": "reverse",
          "order_index": 0
        },
        {
          "strip_id": "center_02",
          "zone": "center",
          "kind": "drive_lane",
          "width_m": 3.3,
          "direction": "reverse",
          "order_index": 1
        },
        {
          "strip_id": "center_03",
          "zone": "center",
          "kind": "median",
          "width_m": 0.3,
          "direction": "none",
          "order_index": 2
        },
        {
          "strip_id": "center_04",
          "zone": "center",
          "kind": "drive_lane",
          "width_m": 3.3,
          "direction": "forward",
          "order_index": 3
        },
        {
          "strip_id": "center_05",
          "zone": "center",
          "kind": "drive_lane",
          "width_m": 3.3,
          "direction": "forward",
          "order_index": 4
        },
        {
          "strip_id": "right_01",
          "zone": "right",
          "kind": "nearroad_furnishing",
          "width_m": 1.5,
          "direction": "none",
          "order_index": 0
        },
        {
          "strip_id": "right_02",
          "zone": "right",
          "kind": "clear_sidewalk",
          "width_m": 2.5,
          "direction": "none",
          "order_index": 1
        },
        {
          "strip_id": "right_03",
          "zone": "right",
          "kind": "frontage_reserve",
          "width_m": 2,
          "direction": "none",
          "order_index": 2
        }
      ],
      "street_furniture_instances": [],
      "start_junction_id": "junction_02",
      "end_junction_id": "junction_03"
    },
    {
      "id": "centerline_09",
      "label": "centerline_09",
      "points": [
        {
          "x": 516.3304427869864,
          "y": 69.47532588086321
        },
        {
          "x": 516.5807931030947,
          "y": 35.172128609323494
        }
      ],
      "road_width_m": 25.500000000000004,
      "reference_width_px": null,
      "forward_drive_lane_count": 2,
      "reverse_drive_lane_count": 2,
      "bike_lane_count": 0,
      "bus_lane_count": 0,
      "parking_lane_count": 0,
      "highway_type": "annotated_centerline",
      "cross_section_mode": "detailed",
      "cross_section_strips": [
        {
          "strip_id": "left_01",
          "zone": "left",
          "kind": "nearroad_furnishing",
          "width_m": 1.5,
          "direction": "none",
          "order_index": 0
        },
        {
          "strip_id": "left_02",
          "zone": "left",
          "kind": "clear_sidewalk",
          "width_m": 2.5,
          "direction": "none",
          "order_index": 1
        },
        {
          "strip_id": "left_03",
          "zone": "left",
          "kind": "frontage_reserve",
          "width_m": 2,
          "direction": "none",
          "order_index": 2
        },
        {
          "strip_id": "center_01",
          "zone": "center",
          "kind": "drive_lane",
          "width_m": 3.3,
          "direction": "reverse",
          "order_index": 0
        },
        {
          "strip_id": "center_02",
          "zone": "center",
          "kind": "drive_lane",
          "width_m": 3.3,
          "direction": "reverse",
          "order_index": 1
        },
        {
          "strip_id": "center_03",
          "zone": "center",
          "kind": "median",
          "width_m": 0.3,
          "direction": "none",
          "order_index": 2
        },
        {
          "strip_id": "center_04",
          "zone": "center",
          "kind": "drive_lane",
          "width_m": 3.3,
          "direction": "forward",
          "order_index": 3
        },
        {
          "strip_id": "center_05",
          "zone": "center",
          "kind": "drive_lane",
          "width_m": 3.3,
          "direction": "forward",
          "order_index": 4
        },
        {
          "strip_id": "right_01",
          "zone": "right",
          "kind": "nearroad_furnishing",
          "width_m": 1.5,
          "direction": "none",
          "order_index": 0
        },
        {
          "strip_id": "right_02",
          "zone": "right",
          "kind": "clear_sidewalk",
          "width_m": 2.5,
          "direction": "none",
          "order_index": 1
        },
        {
          "strip_id": "right_03",
          "zone": "right",
          "kind": "frontage_reserve",
          "width_m": 2,
          "direction": "none",
          "order_index": 2
        }
      ],
      "street_furniture_instances": [
        {
          "instance_id": "centerline_09_furniture_01",
          "centerline_id": "centerline_09",
          "strip_id": "right_03",
          "kind": "tree",
          "station_m": 9.932570035083693,
          "lateral_offset_m": -1,
          "yaw_deg": null
        },
        {
          "instance_id": "centerline_09_furniture_02",
          "centerline_id": "centerline_09",
          "strip_id": "right_03",
          "kind": "tree",
          "station_m": 22.8694072053664,
          "lateral_offset_m": -0.5292731900033747,
          "yaw_deg": null
        },
        {
          "instance_id": "centerline_09_furniture_03",
          "centerline_id": "centerline_09",
          "strip_id": "left_03",
          "kind": "tree",
          "station_m": 22.8694072053664,
          "lateral_offset_m": 0.921416173785099,
          "yaw_deg": null
        }
      ],
      "start_junction_id": "junction_03",
      "end_junction_id": ""
    },
    {
      "id": "centerline_07",
      "label": "centerline_07",
      "points": [
        {
          "x": 516.3304427869864,
          "y": 69.47532588086321
        },
        {
          "x": 989.5177035959566,
          "y": 72.00158052351375
        }
      ],
      "road_width_m": 25.500000000000004,
      "reference_width_px": null,
      "forward_drive_lane_count": 2,
      "reverse_drive_lane_count": 2,
      "bike_lane_count": 0,
      "bus_lane_count": 0,
      "parking_lane_count": 0,
      "highway_type": "annotated_centerline",
      "cross_section_mode": "detailed",
      "cross_section_strips": [
        {
          "strip_id": "left_01",
          "zone": "left",
          "kind": "nearroad_furnishing",
          "width_m": 1.5,
          "direction": "none",
          "order_index": 0
        },
        {
          "strip_id": "left_02",
          "zone": "left",
          "kind": "clear_sidewalk",
          "width_m": 2.5,
          "direction": "none",
          "order_index": 1
        },
        {
          "strip_id": "left_03",
          "zone": "left",
          "kind": "frontage_reserve",
          "width_m": 2,
          "direction": "none",
          "order_index": 2
        },
        {
          "strip_id": "center_01",
          "zone": "center",
          "kind": "drive_lane",
          "width_m": 3.3,
          "direction": "reverse",
          "order_index": 0
        },
        {
          "strip_id": "center_02",
          "zone": "center",
          "kind": "drive_lane",
          "width_m": 3.3,
          "direction": "reverse",
          "order_index": 1
        },
        {
          "strip_id": "center_03",
          "zone": "center",
          "kind": "median",
          "width_m": 0.3,
          "direction": "none",
          "order_index": 2
        },
        {
          "strip_id": "center_04",
          "zone": "center",
          "kind": "drive_lane",
          "width_m": 3.3,
          "direction": "forward",
          "order_index": 3
        },
        {
          "strip_id": "center_05",
          "zone": "center",
          "kind": "drive_lane",
          "width_m": 3.3,
          "direction": "forward",
          "order_index": 4
        },
        {
          "strip_id": "right_01",
          "zone": "right",
          "kind": "nearroad_furnishing",
          "width_m": 1.5,
          "direction": "none",
          "order_index": 0
        },
        {
          "strip_id": "right_02",
          "zone": "right",
          "kind": "clear_sidewalk",
          "width_m": 2.5,
          "direction": "none",
          "order_index": 1
        },
        {
          "strip_id": "right_03",
          "zone": "right",
          "kind": "frontage_reserve",
          "width_m": 2,
          "direction": "none",
          "order_index": 2
        }
      ],
      "street_furniture_instances": [
        {
          "instance_id": "centerline_07_furniture_01",
          "centerline_id": "centerline_07",
          "strip_id": "right_03",
          "kind": "tree",
          "station_m": 37.50610560951235,
          "lateral_offset_m": 1,
          "yaw_deg": null
        },
        {
          "instance_id": "centerline_07_furniture_02",
          "centerline_id": "centerline_07",
          "strip_id": "right_03",
          "kind": "tree",
          "station_m": 63.42033091201828,
          "lateral_offset_m": 1,
          "yaw_deg": null
        },
        {
          "instance_id": "centerline_07_furniture_03",
          "centerline_id": "centerline_07",
          "strip_id": "right_03",
          "kind": "tree",
          "station_m": 87.66288911081291,
          "lateral_offset_m": 1,
          "yaw_deg": null
        },
        {
          "instance_id": "centerline_07_furniture_04",
          "centerline_id": "centerline_07",
          "strip_id": "right_03",
          "kind": "tree",
          "station_m": 116.3256800484683,
          "lateral_offset_m": 1,
          "yaw_deg": null
        },
        {
          "instance_id": "centerline_07_furniture_05",
          "centerline_id": "centerline_07",
          "strip_id": "right_03",
          "kind": "tree",
          "station_m": 138.23797335736967,
          "lateral_offset_m": 1,
          "yaw_deg": null
        },
        {
          "instance_id": "centerline_07_furniture_06",
          "centerline_id": "centerline_07",
          "strip_id": "right_03",
          "kind": "tree",
          "station_m": 169.40743705991034,
          "lateral_offset_m": 1,
          "yaw_deg": null
        },
        {
          "instance_id": "centerline_07_furniture_07",
          "centerline_id": "centerline_07",
          "strip_id": "right_03",
          "kind": "tree",
          "station_m": 195.87642478133898,
          "lateral_offset_m": 1,
          "yaw_deg": null
        },
        {
          "instance_id": "centerline_07_furniture_08",
          "centerline_id": "centerline_07",
          "strip_id": "right_03",
          "kind": "tree",
          "station_m": 219.92932283084664,
          "lateral_offset_m": 1,
          "yaw_deg": null
        },
        {
          "instance_id": "centerline_07_furniture_09",
          "centerline_id": "centerline_07",
          "strip_id": "right_03",
          "kind": "tree",
          "station_m": 250.33837271388754,
          "lateral_offset_m": 1,
          "yaw_deg": null
        },
        {
          "instance_id": "centerline_07_furniture_10",
          "centerline_id": "centerline_07",
          "strip_id": "right_03",
          "kind": "tree",
          "station_m": 272.7339137929601,
          "lateral_offset_m": 0.20733487112815574,
          "yaw_deg": null
        },
        {
          "instance_id": "centerline_07_furniture_11",
          "centerline_id": "centerline_07",
          "strip_id": "right_03",
          "kind": "tree",
          "station_m": 300.3366996927596,
          "lateral_offset_m": 1,
          "yaw_deg": null
        },
        {
          "instance_id": "centerline_07_furniture_12",
          "centerline_id": "centerline_07",
          "strip_id": "left_03",
          "kind": "tree",
          "station_m": 162.9357268420877,
          "lateral_offset_m": -1,
          "yaw_deg": null
        },
        {
          "instance_id": "centerline_07_furniture_13",
          "centerline_id": "centerline_07",
          "strip_id": "left_01",
          "kind": "bench",
          "station_m": 31.02441458999222,
          "lateral_offset_m": -0.4027648652531992,
          "yaw_deg": null
        },
        {
          "instance_id": "centerline_07_furniture_14",
          "centerline_id": "centerline_07",
          "strip_id": "left_01",
          "kind": "bench",
          "station_m": 46.295190203778446,
          "lateral_offset_m": -0.41865795879741086,
          "yaw_deg": null
        },
        {
          "instance_id": "centerline_07_furniture_15",
          "centerline_id": "centerline_07",
          "strip_id": "left_01",
          "kind": "bench",
          "station_m": 65.2955532801386,
          "lateral_offset_m": -0.048525893724646885,
          "yaw_deg": null
        },
        {
          "instance_id": "centerline_07_furniture_16",
          "centerline_id": "centerline_07",
          "strip_id": "left_01",
          "kind": "bench",
          "station_m": 114.47377532565902,
          "lateral_offset_m": -0.75,
          "yaw_deg": null
        },
        {
          "instance_id": "centerline_07_furniture_17",
          "centerline_id": "centerline_07",
          "strip_id": "left_01",
          "kind": "bench",
          "station_m": 131.72290588197248,
          "lateral_offset_m": 0.08299176933160979,
          "yaw_deg": null
        },
        {
          "instance_id": "centerline_07_furniture_18",
          "centerline_id": "centerline_07",
          "strip_id": "left_01",
          "kind": "bench",
          "station_m": 145.32169062460875,
          "lateral_offset_m": 0.1068826375590719,
          "yaw_deg": null
        },
        {
          "instance_id": "centerline_07_furniture_19",
          "centerline_id": "centerline_07",
          "strip_id": "left_01",
          "kind": "bench",
          "station_m": 207.13641814050297,
          "lateral_offset_m": 0.4431846430242734,
          "yaw_deg": null
        },
        {
          "instance_id": "centerline_07_furniture_20",
          "centerline_id": "centerline_07",
          "strip_id": "left_01",
          "kind": "bench",
          "station_m": 220.95949511436757,
          "lateral_offset_m": 0.5405529054327642,
          "yaw_deg": null
        },
        {
          "instance_id": "centerline_07_furniture_21",
          "centerline_id": "centerline_07",
          "strip_id": "left_01",
          "kind": "bench",
          "station_m": 237.12400119990397,
          "lateral_offset_m": 0.5797129633712004,
          "yaw_deg": null
        },
        {
          "instance_id": "centerline_07_furniture_22",
          "centerline_id": "centerline_07",
          "strip_id": "left_01",
          "kind": "tree",
          "station_m": 20.96538027980265,
          "lateral_offset_m": -0.75,
          "yaw_deg": null
        },
        {
          "instance_id": "centerline_07_furniture_23",
          "centerline_id": "centerline_07",
          "strip_id": "left_01",
          "kind": "tree",
          "station_m": 104.41565109777095,
          "lateral_offset_m": -0.6096098179697389,
          "yaw_deg": null
        },
        {
          "instance_id": "centerline_07_furniture_24",
          "centerline_id": "centerline_07",
          "strip_id": "left_01",
          "kind": "tree",
          "station_m": 197.81136698956357,
          "lateral_offset_m": -0.75,
          "yaw_deg": null
        },
        {
          "instance_id": "centerline_07_furniture_25",
          "centerline_id": "centerline_07",
          "strip_id": "left_01",
          "kind": "trash",
          "station_m": 246.5831744834561,
          "lateral_offset_m": 0.4997954920083485,
          "yaw_deg": null
        }
      ],
      "start_junction_id": "junction_03",
      "end_junction_id": "junction_04"
    },
    {
      "id": "centerline_12",
      "label": "centerline_12",
      "points": [
        {
          "x": 989.5177035959566,
          "y": 72.00158052351375
        },
        {
          "x": 989.3608346597296,
          "y": 101.38435967257327
        }
      ],
      "road_width_m": 25.500000000000004,
      "reference_width_px": null,
      "forward_drive_lane_count": 2,
      "reverse_drive_lane_count": 2,
      "bike_lane_count": 0,
      "bus_lane_count": 0,
      "parking_lane_count": 0,
      "highway_type": "annotated_centerline",
      "cross_section_mode": "detailed",
      "cross_section_strips": [
        {
          "strip_id": "left_01",
          "zone": "left",
          "kind": "nearroad_furnishing",
          "width_m": 1.5,
          "direction": "none",
          "order_index": 0
        },
        {
          "strip_id": "left_02",
          "zone": "left",
          "kind": "clear_sidewalk",
          "width_m": 2.5,
          "direction": "none",
          "order_index": 1
        },
        {
          "strip_id": "left_03",
          "zone": "left",
          "kind": "frontage_reserve",
          "width_m": 2,
          "direction": "none",
          "order_index": 2
        },
        {
          "strip_id": "center_01",
          "zone": "center",
          "kind": "drive_lane",
          "width_m": 3.3,
          "direction": "reverse",
          "order_index": 0
        },
        {
          "strip_id": "center_02",
          "zone": "center",
          "kind": "drive_lane",
          "width_m": 3.3,
          "direction": "reverse",
          "order_index": 1
        },
        {
          "strip_id": "center_03",
          "zone": "center",
          "kind": "median",
          "width_m": 0.3,
          "direction": "none",
          "order_index": 2
        },
        {
          "strip_id": "center_04",
          "zone": "center",
          "kind": "drive_lane",
          "width_m": 3.3,
          "direction": "forward",
          "order_index": 3
        },
        {
          "strip_id": "center_05",
          "zone": "center",
          "kind": "drive_lane",
          "width_m": 3.3,
          "direction": "forward",
          "order_index": 4
        },
        {
          "strip_id": "right_01",
          "zone": "right",
          "kind": "nearroad_furnishing",
          "width_m": 1.5,
          "direction": "none",
          "order_index": 0
        },
        {
          "strip_id": "right_02",
          "zone": "right",
          "kind": "clear_sidewalk",
          "width_m": 2.5,
          "direction": "none",
          "order_index": 1
        },
        {
          "strip_id": "right_03",
          "zone": "right",
          "kind": "frontage_reserve",
          "width_m": 2,
          "direction": "none",
          "order_index": 2
        }
      ],
      "street_furniture_instances": [],
      "start_junction_id": "junction_04",
      "end_junction_id": "junction_05"
    },
    {
      "id": "centerline_13",
      "label": "centerline_13",
      "points": [
        {
          "x": 989.3608346597296,
          "y": 101.38435967257327
        },
        {
          "x": 989.0116264659366,
          "y": 166.79378668883498
        }
      ],
      "road_width_m": 25.500000000000004,
      "reference_width_px": null,
      "forward_drive_lane_count": 2,
      "reverse_drive_lane_count": 2,
      "bike_lane_count": 0,
      "bus_lane_count": 0,
      "parking_lane_count": 0,
      "highway_type": "annotated_centerline",
      "cross_section_mode": "detailed",
      "cross_section_strips": [
        {
          "strip_id": "left_01",
          "zone": "left",
          "kind": "nearroad_furnishing",
          "width_m": 1.5,
          "direction": "none",
          "order_index": 0
        },
        {
          "strip_id": "left_02",
          "zone": "left",
          "kind": "clear_sidewalk",
          "width_m": 2.5,
          "direction": "none",
          "order_index": 1
        },
        {
          "strip_id": "left_03",
          "zone": "left",
          "kind": "frontage_reserve",
          "width_m": 2,
          "direction": "none",
          "order_index": 2
        },
        {
          "strip_id": "center_01",
          "zone": "center",
          "kind": "drive_lane",
          "width_m": 3.3,
          "direction": "reverse",
          "order_index": 0
        },
        {
          "strip_id": "center_02",
          "zone": "center",
          "kind": "drive_lane",
          "width_m": 3.3,
          "direction": "reverse",
          "order_index": 1
        },
        {
          "strip_id": "center_03",
          "zone": "center",
          "kind": "median",
          "width_m": 0.3,
          "direction": "none",
          "order_index": 2
        },
        {
          "strip_id": "center_04",
          "zone": "center",
          "kind": "drive_lane",
          "width_m": 3.3,
          "direction": "forward",
          "order_index": 3
        },
        {
          "strip_id": "center_05",
          "zone": "center",
          "kind": "drive_lane",
          "width_m": 3.3,
          "direction": "forward",
          "order_index": 4
        },
        {
          "strip_id": "right_01",
          "zone": "right",
          "kind": "nearroad_furnishing",
          "width_m": 1.5,
          "direction": "none",
          "order_index": 0
        },
        {
          "strip_id": "right_02",
          "zone": "right",
          "kind": "clear_sidewalk",
          "width_m": 2.5,
          "direction": "none",
          "order_index": 1
        },
        {
          "strip_id": "right_03",
          "zone": "right",
          "kind": "frontage_reserve",
          "width_m": 2,
          "direction": "none",
          "order_index": 2
        }
      ],
      "street_furniture_instances": [],
      "start_junction_id": "junction_05",
      "end_junction_id": ""
    },
    {
      "id": "centerline_10",
      "label": "centerline_10",
      "points": [
        {
          "x": 989.5177035959566,
          "y": 72.00158052351375
        },
        {
          "x": 990.0237807259766,
          "y": -22.79062564180748
        }
      ],
      "road_width_m": 25.500000000000004,
      "reference_width_px": null,
      "forward_drive_lane_count": 2,
      "reverse_drive_lane_count": 2,
      "bike_lane_count": 0,
      "bus_lane_count": 0,
      "parking_lane_count": 0,
      "highway_type": "annotated_centerline",
      "cross_section_mode": "detailed",
      "cross_section_strips": [
        {
          "strip_id": "left_01",
          "zone": "left",
          "kind": "nearroad_furnishing",
          "width_m": 1.5,
          "direction": "none",
          "order_index": 0
        },
        {
          "strip_id": "left_02",
          "zone": "left",
          "kind": "clear_sidewalk",
          "width_m": 2.5,
          "direction": "none",
          "order_index": 1
        },
        {
          "strip_id": "left_03",
          "zone": "left",
          "kind": "frontage_reserve",
          "width_m": 2,
          "direction": "none",
          "order_index": 2
        },
        {
          "strip_id": "center_01",
          "zone": "center",
          "kind": "drive_lane",
          "width_m": 3.3,
          "direction": "reverse",
          "order_index": 0
        },
        {
          "strip_id": "center_02",
          "zone": "center",
          "kind": "drive_lane",
          "width_m": 3.3,
          "direction": "reverse",
          "order_index": 1
        },
        {
          "strip_id": "center_03",
          "zone": "center",
          "kind": "median",
          "width_m": 0.3,
          "direction": "none",
          "order_index": 2
        },
        {
          "strip_id": "center_04",
          "zone": "center",
          "kind": "drive_lane",
          "width_m": 3.3,
          "direction": "forward",
          "order_index": 3
        },
        {
          "strip_id": "center_05",
          "zone": "center",
          "kind": "drive_lane",
          "width_m": 3.3,
          "direction": "forward",
          "order_index": 4
        },
        {
          "strip_id": "right_01",
          "zone": "right",
          "kind": "nearroad_furnishing",
          "width_m": 1.5,
          "direction": "none",
          "order_index": 0
        },
        {
          "strip_id": "right_02",
          "zone": "right",
          "kind": "clear_sidewalk",
          "width_m": 2.5,
          "direction": "none",
          "order_index": 1
        },
        {
          "strip_id": "right_03",
          "zone": "right",
          "kind": "frontage_reserve",
          "width_m": 2,
          "direction": "none",
          "order_index": 2
        }
      ],
      "street_furniture_instances": [
        {
          "instance_id": "centerline_10_furniture_01",
          "centerline_id": "centerline_10",
          "strip_id": "right_03",
          "kind": "tree",
          "station_m": 31.132992470853555,
          "lateral_offset_m": 1,
          "yaw_deg": null
        }
      ],
      "start_junction_id": "junction_04",
      "end_junction_id": ""
    },
    {
      "id": "centerline_11",
      "label": "centerline_11",
      "points": [
        {
          "x": 989.3608346597296,
          "y": 101.38435967257327
        },
        {
          "x": 1019.0083040268086,
          "y": 101.4795918367347
        }
      ],
      "road_width_m": 25.500000000000004,
      "reference_width_px": null,
      "forward_drive_lane_count": 2,
      "reverse_drive_lane_count": 2,
      "bike_lane_count": 0,
      "bus_lane_count": 0,
      "parking_lane_count": 0,
      "highway_type": "annotated_centerline",
      "cross_section_mode": "detailed",
      "cross_section_strips": [
        {
          "strip_id": "left_01",
          "zone": "left",
          "kind": "nearroad_furnishing",
          "width_m": 1.5,
          "direction": "none",
          "order_index": 0
        },
        {
          "strip_id": "left_02",
          "zone": "left",
          "kind": "clear_sidewalk",
          "width_m": 2.5,
          "direction": "none",
          "order_index": 1
        },
        {
          "strip_id": "left_03",
          "zone": "left",
          "kind": "frontage_reserve",
          "width_m": 2,
          "direction": "none",
          "order_index": 2
        },
        {
          "strip_id": "center_01",
          "zone": "center",
          "kind": "drive_lane",
          "width_m": 3.3,
          "direction": "reverse",
          "order_index": 0
        },
        {
          "strip_id": "center_02",
          "zone": "center",
          "kind": "drive_lane",
          "width_m": 3.3,
          "direction": "reverse",
          "order_index": 1
        },
        {
          "strip_id": "center_03",
          "zone": "center",
          "kind": "median",
          "width_m": 0.3,
          "direction": "none",
          "order_index": 2
        },
        {
          "strip_id": "center_04",
          "zone": "center",
          "kind": "drive_lane",
          "width_m": 3.3,
          "direction": "forward",
          "order_index": 3
        },
        {
          "strip_id": "center_05",
          "zone": "center",
          "kind": "drive_lane",
          "width_m": 3.3,
          "direction": "forward",
          "order_index": 4
        },
        {
          "strip_id": "right_01",
          "zone": "right",
          "kind": "nearroad_furnishing",
          "width_m": 1.5,
          "direction": "none",
          "order_index": 0
        },
        {
          "strip_id": "right_02",
          "zone": "right",
          "kind": "clear_sidewalk",
          "width_m": 2.5,
          "direction": "none",
          "order_index": 1
        },
        {
          "strip_id": "right_03",
          "zone": "right",
          "kind": "frontage_reserve",
          "width_m": 2,
          "direction": "none",
          "order_index": 2
        }
      ],
      "street_furniture_instances": [],
      "start_junction_id": "junction_05",
      "end_junction_id": ""
    }
  ],
  "junctions": [
    {
      "id": "junction_01",
      "label": "junction_01",
      "x": 291.7560039751718,
      "y": 99.22703610030007,
      "kind": "cross_junction",
      "connected_centerline_ids": [
        "centerline_04",
        "centerline_05",
        "centerline_02",
        "centerline_03"
      ],
      "crosswalk_depth_m": 3,
      "source_mode": "explicit"
    },
    {
      "id": "junction_02",
      "label": "junction_02",
      "x": 516.1008267201856,
      "y": 100.9375,
      "kind": "t_junction",
      "connected_centerline_ids": [
        "centerline_05",
        "centerline_01",
        "centerline_08"
      ],
      "crosswalk_depth_m": 3,
      "source_mode": "explicit"
    },
    {
      "id": "junction_03",
      "label": "junction_03",
      "x": 516.3304427869864,
      "y": 69.47532588086321,
      "kind": "t_junction",
      "connected_centerline_ids": [
        "centerline_08",
        "centerline_09",
        "centerline_07"
      ],
      "crosswalk_depth_m": 3,
      "source_mode": "explicit"
    },
    {
      "id": "junction_04",
      "label": "junction_04",
      "x": 989.5177035959566,
      "y": 72.00158052351375,
      "kind": "t_junction",
      "connected_centerline_ids": [
        "centerline_07",
        "centerline_12",
        "centerline_10"
      ],
      "crosswalk_depth_m": 3,
      "source_mode": "explicit"
    },
    {
      "id": "junction_05",
      "label": "junction_05",
      "x": 989.3608346597296,
      "y": 101.38435967257327,
      "kind": "t_junction",
      "connected_centerline_ids": [
        "centerline_12",
        "centerline_13",
        "centerline_11"
      ],
      "crosswalk_depth_m": 3,
      "source_mode": "explicit"
    }
  ],
  "roundabouts": [],
  "control_points": [],
  "building_regions": [
    {
      "id": "building_region_01",
      "label": "building_region_01",
      "center_px": {
        "x": 638.4857579495866,
        "y": 144.04794254658384
      },
      "width_px": 209.26707296864356,
      "height_px": 48.89196983141083,
      "yaw_deg": 0
    },
    {
      "id": "building_region_02",
      "label": "building_region_02",
      "center_px": {
        "x": 866.9312662259947,
        "y": 144.51814829192546
      },
      "width_px": 209.703080407284,
      "height_px": 49.51184006211177,
      "yaw_deg": 0
    },
    {
      "id": "building_region_03",
      "label": "building_region_03",
      "center_px": {
        "x": 629.4014840455893,
        "y": 26.20660492457853
      },
      "width_px": 194.5158807608035,
      "height_px": 46.41720275066549,
      "yaw_deg": 0
    },
    {
      "id": "building_region_04",
      "label": "building_region_04",
      "center_px": {
        "x": 867.2199738542836,
        "y": 28.660159716060335
      },
      "width_px": 206.20795050726372,
      "height_px": 49.11352040816327,
      "yaw_deg": 0
    },
    {
      "id": "building_region_05",
      "label": "building_region_05",
      "center_px": {
        "x": 401.3342416821638,
        "y": 143.92656111357587
      },
      "width_px": 184.34865865110197,
      "height_px": 50.011507320319424,
      "yaw_deg": 0
    },
    {
      "id": "building_region_06",
      "label": "building_region_06",
      "center_px": {
        "x": 405.09804643626524,
        "y": 44.21937389086069
      },
      "width_px": 189.78814604776193,
      "height_px": 73.94368345164152,
      "yaw_deg": 0
    }
  ],
  "functional_zones": [
    {
      "id": "functional_zone_01",
      "label": "functional_zone_01",
      "kind": "plaza",
      "points": [
        {
          "x": 532.5112039918249,
          "y": 88.36568322981367
        },
        {
          "x": 975.9496234648598,
          "y": 90.10509094942324
        },
        {
          "x": 975.7752204894036,
          "y": 113.146350931677
        },
        {
          "x": 530.3500211743477,
          "y": 110.21198425022183
        }
      ],
      "furniture_instances": []
    },
    {
      "id": "functional_zone_02",
      "label": "functional_zone_02",
      "kind": "plaza",
      "points": [
        {
          "x": 68.14678426101527,
          "y": 121.74911268855368
        },
        {
          "x": 264.1238791405056,
          "y": 122.05315550133096
        },
        {
          "x": 263.82456592587135,
          "y": 164.762921472937
        },
        {
          "x": 66.82462116330025,
          "y": 166.7498059006211
        }
      ],
      "furniture_instances": []
    },
    {
      "id": "functional_zone_03",
      "label": "functional_zone_03",
      "kind": "plaza",
      "points": [
        {
          "x": 67.92995894017787,
          "y": 72.2844110470275
        },
        {
          "x": 68.56158052696507,
          "y": 5.79331188997338
        },
        {
          "x": 265.31406160814566,
          "y": 3.895990461401952
        },
        {
          "x": 265.8679088950673,
          "y": 74.98072870452529
        }
      ],
      "furniture_instances": []
    }
  ],
  "junction_compositions": []
}
